atwc/__init__.py
atwc/__version__.py
atwc/browsers.py
atwc/client.py
atwc/utils.py
atwc-1.1.0.dist-info/LICENSE
atwc-1.1.0.dist-info/METADATA
atwc-1.1.0.dist-info/WHEEL
atwc-1.1.0.dist-info/RECORD
